hfst/version.py
hfst/hfst_regex_extensions.cpp
hfst/hfst_pmatch_extensions.cpp
hfst/hfst_pmatch_tokenize_extensions.cpp
hfst/hfst_lookup_extensions.cpp
hfst/__init__.py
hfst/hfst_sfst_extensions.cpp
hfst/hfst_file_extensions.cpp
hfst/libhfst.i
hfst/hfst_lexc_extensions.cpp
hfst/libhfst.py
hfst/libhfst_wrap.cpp
hfst/hfst_rules_extensions.cpp
hfst/docstrings.i
hfst/hfst_xfst_extensions.cpp
hfst/_libhfst.cpython-38-darwin.so
hfst/hfst_prolog_extensions.cpp
hfst/hfst_extensions.cpp
hfst/xerox_rules/__init__.py
hfst/exceptions/__init__.py
hfst/.dylibs/libreadline.8.2.dylib
hfst/.dylibs/libncurses.6.dylib
hfst/.dylibs/libfst.22.dylib
hfst/.dylibs/libfoma.0.10.0.dylib
hfst/.dylibs/libicui18n.73.2.dylib
hfst/.dylibs/libhfst.55.dylib
hfst/.dylibs/libz.1.3.dylib
hfst/.dylibs/libicudata.73.2.dylib
hfst/.dylibs/libicuuc.73.2.dylib
hfst/sfst_rules/__init__.py
hfst-3.16.0.1.dist-info/RECORD
hfst-3.16.0.1.dist-info/LICENSE
hfst-3.16.0.1.dist-info/WHEEL
hfst-3.16.0.1.dist-info/top_level.txt
hfst-3.16.0.1.dist-info/METADATA
