Metadata-Version: 2.1
Name: hfst
Version: 3.16.0.1
Summary: Python SWIG-bound interface for HFST
Home-page: UNKNOWN
Author: HFST team
Author-email: hfst-bugs@helsinki.fi
License: GNU GPL3
Project-URL: Homepage, https://hfst.github.io/
Project-URL: Documentation, https://github.com/hfst/python/wiki
Project-URL: Repository, https://github.com/reynoldsnlp/hfst-python.git
Keywords: Finite-state transducer,morphology,morphological,part of speech,tagger,Natural Language Processing,NLP
Platform: UNKNOWN
Classifier: Development Status :: 5 - Production/Stable
Classifier: Intended Audience :: Developers
Classifier: Intended Audience :: Science/Research
Classifier: License :: OSI Approved :: GNU General Public License v3 (GPLv3)
Classifier: Operating System :: MacOS
Classifier: Operating System :: POSIX :: Linux
Classifier: Programming Language :: C++
Classifier: Programming Language :: Python
Classifier: Programming Language :: Python :: 3.6
Classifier: Programming Language :: Python :: 3.7
Classifier: Programming Language :: Python :: 3.8
Classifier: Programming Language :: Python :: 3.9
Classifier: Programming Language :: Python :: 3.10
Classifier: Programming Language :: Python :: 3.11
Classifier: Programming Language :: Python :: 3.12
Classifier: Programming Language :: Python :: Implementation :: CPython
Classifier: Programming Language :: Python :: Implementation :: PyPy
Classifier: Topic :: Education
Classifier: Topic :: Scientific/Engineering
Classifier: Topic :: Scientific/Engineering :: Artificial Intelligence
Classifier: Topic :: Scientific/Engineering :: Human Machine Interfaces
Classifier: Topic :: Text Processing :: Linguistic
Classifier: Topic :: Utilities
Requires-Python: >=3.6
License-File: LICENSE
